[{"name":"识记并正确书写现代常用规范汉字","childs":[{"name":"字形","stars":4},{"name":"字音+字形","stars":2}]},{"name":"正确使用词语（包括熟语）","childs":[{"name":"词语","stars":3},{"name":"成语","stars":5},{"name":"词语+熟语","stars":5}]},{"name":"辨析并修改病句","childs":[{"name":"辨析病句","stars":5},{"name":"修改病句","stars":2}]},{"name":"扩展语句，压缩语段","childs":[{"name":"扩展语句","stars":3},{"name":"压缩语段","stars":4}]},{"name":"选用、仿用、变换句式 修辞","childs":[{"name":"选用、变换句式","stars":3},{"name":"仿用句式","stars":4},{"name":"句式+修辞","stars":5}]},{"name":"语言表达简明、连贯、得体、准确、鲜明、生动","childs":[{"name":"连贯","stars":5},{"name":"得体","stars":3},{"name":"语言综合表达","stars":5}]},{"name":"图文转换","childs":[{"name":"数据分类","stars":4},{"name":"图片解读类","stars":4}]},{"name":"文言文阅读","childs":[{"name":"理解文言词语","stars":5},{"name":"筛选信息","stars":5},{"name":"概括内容和观点","stars":5},{"name":"句式、翻译","stars":5},{"name":"断句","stars":5}]},{"name":"古代诗歌鉴赏","childs":[{"name":"形象","stars":5},{"name":"语言","stars":5},{"name":"表达技巧","stars":5},{"name":"思想内容、观点态度","stars":5}]},{"name":"默写常见的名句名篇","childs":[{"name":"记忆型默写","stars":5},{"name":"情境型默写","stars":5}]},{"name":"文学类文本阅读","childs":[{"name":"小说","stars":5},{"name":"散文","stars":5}]},{"name":"实用类文本阅读","childs":[{"name":"传记","stars":5},{"name":"新闻","stars":2},{"name":"科普","stars":3}]},{"name":"集合与常用逻辑用语","childs":[{"name":"集合及其相关运算","stars":5},{"name":"命题及其关系、充分条件与必要条件","stars":4},{"name":"简单的逻辑联结词、全称量词与存在量词","stars":3}]},{"name":"函数概念及其基本性质","childs":[{"name":"函数及其表示","stars":4},{"name":"函数的单调性与最值","stars":2},{"name":"函数的奇偶性与周期性","stars":4}]},{"name":"基本初等函数","childs":[{"name":"指数与指数函数","stars":3},{"name":"对数与对数函数","stars":4},{"name":"二次函数与幂函数","stars":3}]},{"name":"函数的图象、函数的应用","childs":[{"name":"函数的图象","stars":3},{"name":"函数与方程","stars":3},{"name":"函数模型及其综合应用","stars":3}]},{"name":"导数及其应用","childs":[{"name":"导数的概念及运算","stars":3},{"name":"导数的应用","stars":5}]},{"name":"三角函数","childs":[{"name":"三角函数的有关概念、同角三角函数的关系式及诱导公式","stars":3},{"name":"三角函数的图象及其变换  4颗星","stars":4},{"name":"三角函数的性质及其应用  5颗星","stars":5}]},{"name":"三角恒等变换与解三角形","childs":[{"name":"三角恒等变换","stars":5},{"name":"正、余弦定理及解三角形","stars":5}]},{"name":"平面向量","childs":[{"name":"平面向量的概念、线性运算与基本定理","stars":5},{"name":"平面向量的数量积","stars":5},{"name":"平面向量的综合应用","stars":5}]},{"name":"数列","childs":[{"name":"数列的概念与简单表示法","stars":2},{"name":"等差数列及其前n项和","stars":5},{"name":"等比数列及其前n项和","stars":5},{"name":"数列求和","stars":3},{"name":"数列的综合问题及应用","stars":4}]},{"name":"不等式","childs":[{"name":"不等式的性质及应用","stars":3},{"name":"一元二次不等式的解法及应用","stars":4},{"name":"二元一次不等式（组）表示的平面区域及线性规划","stars":5},{"name":"基本不等式及其应用","stars":3}]},{"name":"立体几何","childs":[{"name":"空间几何体的结构特征、三视图与直观图","stars":5},{"name":"空间几何体的表面积与体积","stars":5},{"name":"空间点、线、面的位置关系","stars":3},{"name":"直线、平面平行的判定与性质","stars":4},{"name":"直线、平面垂直的判定与性质","stars":5}]},{"name":"直线与圆的方程","childs":[{"name":"直线方程与两直线的位置关系","stars":2},{"name":"圆的方程及点、线、圆的位置关系","stars":5}]},{"name":"圆锥曲线与方程","childs":[{"name":"椭圆及其性质","stars":5},{"name":"双曲线及其性质","stars":4},{"name":"抛物线及其性质","stars":5},{"name":"直线与圆锥曲线的位置关系","stars":4},{"name":"圆锥曲线的综合问题","stars":5}]},{"name":"概率","childs":[{"name":"随机事件的概率、古典概型","stars":5},{"name":"几何概型","stars":2}]},{"name":"统计与统计案例","childs":[{"name":"随机抽样与用样本估计总体","stars":5},{"name":"变量的相关性与统计案例","stars":3}]},{"name":"推理与证明","childs":[{"name":"合情推理与演绎推理","stars":4},{"name":"直接证明与间接证明","stars":4}]},{"name":"几何证明选讲","childs":[{"name":"相似三角形与比例线段","stars":2},{"name":"与圆有关的综合问题","stars":4}]},{"name":"坐标系与参数方程","childs":[{"name":"极坐标与直角坐标","stars":3},{"name":"参数方程","stars":3}]},{"name":"不等式选讲","childs":[{"name":"绝对值不等式","stars":2},{"name":"不等式的证明","stars":1}]},{"name":"集合与常用逻辑用语","childs":[{"name":"集合及其相关运算","stars":5},{"name":"命题及其关系、充分条件与必要条件","stars":5},{"name":"简单的逻辑联结词、全称量词与存在量词","stars":3}]},{"name":"函数概念及其基本性质","childs":[{"name":"函数及其表示","stars":3},{"name":"函数的单调性","stars":2},{"name":"函数的奇偶性与周期性","stars":3}]},{"name":"基本初等函数","childs":[{"name":"指数与指数函数","stars":2},{"name":"对数与对数函数","stars":3},{"name":"二次函数与幂函数","stars":2}]},{"name":"函数的图象、函数的应用","childs":[{"name":"函数的图象","stars":4},{"name":"函数与方程","stars":3},{"name":"函数模型及其应用","stars":2}]},{"name":"导数及其应用","childs":[{"name":"导数的概念及运算","stars":2},{"name":"导数的应用","stars":5},{"name":"定积分的计算","stars":2}]},{"name":"三角函数","childs":[{"name":"三角函数的有关概念、同角三角函数关系式及诱导公式","stars":2},{"name":"三角函数的图象及其变换","stars":3},{"name":"三角函数的性质及其应用","stars":4}]},{"name":"三角恒等变换与解三角形","childs":[{"name":"三角恒等变换","stars":3},{"name":"正、余弦定理及解三角形","stars":5}]},{"name":"平面向量","childs":[{"name":"平面向量的概念、线性运算与基本定理","stars":4},{"name":"平面向量的数量积及其应用","stars":4},{"name":"平面向量的综合应用","stars":5}]},{"name":"数列","childs":[{"name":"数列的概念与简单表示法","stars":2},{"name":"等差数列及其前n项和","stars":5},{"name":"等比数列及其前n项和","stars":5},{"name":"数列求和","stars":3},{"name":"数列的综合问题及应用","stars":3}]},{"name":"不等式","childs":[{"name":"不等式的性质及应用","stars":3},{"name":"一元二次不等式的解法及应用","stars":4},{"name":"二元一次不等式（组）表示的平面区域及线性规划","stars":5},{"name":"基本不等式及其应用","stars":4}]},{"name":"立体几何","childs":[{"name":"空间几何体的结构特征、三视图、直观图表面积和体积","stars":5},{"name":"空间点、线、面的位置关系","stars":3},{"name":"直线、平面平行的判定与性质","stars":4},{"name":"直线、平面垂直的判定与性质","stars":5}]},{"name":"空间向量与立体几何","childs":[{"name":"空间直角坐标系、空间向量及其运算","stars":2},{"name":"与空间角和距离有关的计算","stars":4}]},{"name":"直线与圆的方程","childs":[{"name":"直线方程与两直线的位置关系","stars":2},{"name":"圆的方程及点、线、圆的位置关系","stars":4}]},{"name":"圆锥曲线与方程","childs":[{"name":"椭圆及其性质","stars":5},{"name":"双曲线及其性质","stars":4},{"name":"抛物线及其性质","stars":4},{"name":"直线与圆锥曲线的位置关系","stars":5},{"name":"圆锥曲线的综合问题","stars":5}]},{"name":"计数原理","childs":[{"name":"排列与组合","stars":5},{"name":"二项式定理","stars":5}]},{"name":"概率","childs":[{"name":"随机事件的概率、古典概型","stars":5},{"name":"几何概型","stars":2}]},{"name":"随机变量及其分布列","childs":[{"name":"事件的独立性与条件概率","stars":3},{"name":"独立重复试验与二项分布、正态分布","stars":3},{"name":"离散型随机变量的分布列、期望与方差","stars":5}]},{"name":"统计与统计案例","childs":[{"name":"随机抽样与用样本估计总体","stars":5},{"name":"变量的相关性与统计案例","stars":3}]},{"name":"推理与证明","childs":[{"name":"合情推理与演绎推理","stars":4},{"name":"直接证明与间接证明","stars":3},{"name":"数学归纳法","stars":3}]},{"name":"几何证明选讲","childs":[{"name":"相似三角形与比例线段","stars":2},{"name":"与圆有关的综合问题","stars":4}]},{"name":"坐标系与参数方程","childs":[{"name":"极坐标与直角坐标","stars":4},{"name":"参数方程","stars":4}]},{"name":"不等式选讲","childs":[{"name":"绝对值不等式","stars":4},{"name":"不等式的证明","stars":2}]},{"name":"运动的描述  匀变速直线运动","childs":[{"name":"描述运动的基本物理量","stars":2},{"name":"匀变速直线运动的规律及应用","stars":5},{"name":"运动的图象问题","stars":5}]},{"name":"相互作用","childs":[{"name":"弹力和摩擦力的分析与计算","stars":2},{"name":"力的合成和分解","stars":4},{"name":"受力分析 共点力平衡","stars":5}]},{"name":"牛顿运动定律","childs":[{"name":"牛顿运动定理的理解超重和失重","stars":2},{"name":"牛顿运动定律的应用","stars":5},{"name":"动力学的图象问题","stars":4}]},{"name":"曲线运动","childs":[{"name":"曲线运动 运动的合成与分解","stars":4},{"name":"平抛运动的规律及应用","stars":4},{"name":"圆周运动的规律及应用","stars":5}]},{"name":"万有引力与航天","childs":[{"name":"行星或卫星的圆周运动","stars":5},{"name":"卫星的发射 椭圆轨道与变轨","stars":5}]},{"name":"机械能及其守恒定律","childs":[{"name":"功与功率","stars":3},{"name":"动能定理及其应用","stars":5},{"name":"机械能守恒定律及其应用","stars":5},{"name":"功能关系  能量守恒","stars":5}]},{"name":"电场","childs":[{"name":"电荷守恒定律  库仑定律","stars":3},{"name":"电场的强弱及描绘","stars":5},{"name":"电场力功 电势能","stars":5},{"name":"电容器 带电粒子在电场中的运动","stars":5}]},{"name":"恒定电流","childs":[{"name":"部分电路欧姆定律及应用","stars":2},{"name":"闭合电路欧姆定律及应用","stars":3}]},{"name":"磁场","childs":[{"name":"电流的磁场 安培力","stars":4},{"name":"洛伦兹力 带电粒子在匀强磁场中的运动","stars":5},{"name":"带电粒子在复合场中的运动","stars":5},{"name":"现代科技中的电磁场问题","stars":2}]},{"name":"电磁感应","childs":[{"name":"电磁感应现象  楞次定律","stars":4},{"name":"法拉第电磁感应定律 自感","stars":4},{"name":"电磁感应中的电路问题","stars":2},{"name":"电磁感应中的图象问题","stars":4},{"name":"电磁感应中的动力学与能量问题","stars":4}]},{"name":"交变电流","childs":[{"name":"交变电流的产生和描述","stars":3},{"name":"变压器的原理及电路分析","stars":5},{"name":"远距离输电问题","stars":2}]},{"name":"实验","childs":[{"name":"实验一：研究匀变速直线运动","stars":2},{"name":"实验二： 探究弹力和弹簧伸长的关系","stars":3},{"name":"实验三：验证力的平行四边形定则","stars":2},{"name":"实验四：验证牛顿运动定律","stars":4},{"name":"实验五：探究动能定理","stars":1},{"name":"实验六：验证机械能守恒定律","stars":2},{"name":"实验七 ：电阻的测量","stars":5},{"name":"实验八 ：测定金属的电阻率","stars":5},{"name":"实验九：描绘小电珠的伏安特性曲线","stars":4},{"name":"实验十：测定电池的电动势和内阻","stars":4},{"name":"实验十一 ：练习使用多用电表","stars":4},{"name":"实验十二：传感器的简单使用","stars":1}]},{"name":"热学","childs":[{"name":"分子运动论 内能","stars":4},{"name":"气体 固体与液体","stars":5},{"name":"热力学定律和能量守恒","stars":5},{"name":"实验：用油膜法估测分子的大小","stars":1}]},{"name":"机械振动  机械波","childs":[{"name":"简谐运动 受迫振动","stars":3},{"name":"机械波的形成与传播","stars":5},{"name":"波的干涉和衍射","stars":1},{"name":"实验一：探究单摆的运动、用单摆测定重力加速度","stars":1}]},{"name":"光学 电磁波 相对论简介","childs":[{"name":"光的折射  全反射","stars":5},{"name":"光的波动性","stars":2},{"name":"电磁波 相对论","stars":2},{"name":"实验二：测定玻璃的折射率","stars":1},{"name":"实验三：用双缝干涉测光的波长","stars":1}]},{"name":"碰撞与动量守恒定律","childs":[{"name":"动量 冲量 动量定理","stars":2},{"name":"动量守恒定律及其应用","stars":5},{"name":"碰撞及其可能性判断","stars":3},{"name":"实验：验证动量守恒定理","stars":1}]},{"name":"波粒二象性 原子结构与原子核","childs":[{"name":"光电效应 光的波粒二象性","stars":3},{"name":"原子结构 能级跃迁","stars":4},{"name":"原子核 核能","stars":5}]},{"name":"物质的分类与化学用语","childs":[{"name":"物质的组成与分类","stars":1},{"name":"化学用语","stars":4},{"name":"分散系","stars":2}]},{"name":"物质的量","childs":[{"name":"物质的量及相关物理量","stars":5},{"name":"一定物质的量浓度溶液的配制","stars":4}]},{"name":"离子反应","childs":[{"name":"离子方程式","stars":4},{"name":"离子共存","stars":4}]},{"name":"氧化还原反应","childs":[{"name":"氧化还原反应的概念与判断","stars":2},{"name":"氧化性、还原性的强弱对比","stars":1},{"name":"氧化还原反应方程式的配平","stars":1}]},{"name":"物质结构 元素周期律","childs":[{"name":"物质的结构与性质","stars":3},{"name":"化学键","stars":2},{"name":"元素周期律和元素周期表","stars":5}]},{"name":"化学反应与能量变化","childs":[{"name":"能量转化及其应用","stars":3},{"name":"热化学方程式的书写","stars":5},{"name":"盖斯定律的应用","stars":4},{"name":"原电池","stars":5},{"name":"电解池","stars":5},{"name":"金属腐蚀及其防护","stars":3}]},{"name":"化学反应速率 化学平衡","childs":[{"name":"化学反应速率","stars":3},{"name":"化学平衡状态的判断依据","stars":4},{"name":"化学平衡的移动","stars":5},{"name":"化学平衡常数的转化率","stars":5}]},{"name":"水溶液中的离子平衡","childs":[{"name":"电离平衡","stars":3},{"name":"水的电离","stars":2},{"name":"盐类水解","stars":3},{"name":"溶液中微粒浓度的大小比较","stars":5},{"name":"沉淀溶解平衡","stars":3}]},{"name":"金属元素及其化合物","childs":[{"name":"钠及其重要化合物","stars":3},{"name":"铝及其重要化合物","stars":5},{"name":"铁、铜及其重要化合物","stars":4}]},{"name":"非金属元素及其化合物","childs":[{"name":"碳、硅及其化合物","stars":3},{"name":"氯及其化合物","stars":4},{"name":"硫及其化合物","stars":4},{"name":"氮及其化合物","stars":4}]},{"name":"常见有机化合物","childs":[{"name":"烃的结构与性质","stars":4},{"name":"饮食中的有机化合物","stars":3}]},{"name":"基本仪器和基本操作","childs":[{"name":"基本仪器与药品的保存","stars":3},{"name":"基本操作与实验安全","stars":5}]},{"name":"基本实验方法","childs":[{"name":"物质的检验","stars":3},{"name":"物质的分离与提纯","stars":3},{"name":"常见气体的制备","stars":2}]},{"name":"化学实验方法","childs":[{"name":"实验方案的设计与评价","stars":5},{"name":"实验方案的解读","stars":4},{"name":"探究性实验","stars":4}]},{"name":"化学与技术","childs":[{"name":"化学与工农业生产","stars":3},{"name":"化学与资源开发利用","stars":2},{"name":"化学与材料的制造和应用","stars":1}]},{"name":"物质结构与性质","childs":[{"name":"原子结构与性质","stars":5},{"name":"分子结构与性质","stars":5},{"name":"晶体结构与性质","stars":4}]},{"name":"有机化学基础","childs":[{"name":"有机物的结构与性质","stars":5},{"name":"有机反应类型","stars":5},{"name":"有机合成与推断","stars":5}]},{"name":"细胞的分子组成","childs":[{"name":"组成细胞的元素和无机物","stars":2},{"name":"蛋白质的结构和功能","stars":4},{"name":"核酸的结构和功能","stars":4},{"name":"细胞中的糖类和脂质","stars":2},{"name":"有机物的鉴定","stars":4}]},{"name":"细胞的结构功能","childs":[{"name":"多种多样的细胞","stars":3},{"name":"细胞膜和细胞核","stars":3},{"name":"细胞器的结构和功能","stars":5}]},{"name":"物质出入细胞的方式","childs":[{"name":"渗透作用的原理和应用","stars":3},{"name":"物质出入细胞的方式","stars":3}]},{"name":"酶与ATP","childs":[{"name":"酶在代谢中的作用","stars":4},{"name":"ATP在能量代谢中的作用","stars":2}]},{"name":"细胞呼吸和光合作用","childs":[{"name":"细胞呼吸的过程和原理","stars":5},{"name":"细胞呼吸的影响因素及应用","stars":5},{"name":"光合色素的提取、分离与作用","stars":4},{"name":"光合作用的过程和影响因素","stars":5},{"name":"光合作用与细胞呼吸的综合应用","stars":5}]},{"name":"细胞的生命历程","childs":[{"name":"细胞周期和细胞的有丝分裂","stars":4},{"name":"细胞有丝分裂的观察","stars":3},{"name":"细胞的分化和全能性","stars":4},{"name":"细胞的衰老、凋亡与癌变","stars":4}]},{"name":"遗传的细胞基础","childs":[{"name":"减数分裂与受精作用","stars":4},{"name":"减数分裂与有丝分裂","stars":3}]},{"name":"遗传的分子基础","childs":[{"name":"遗传物质的探索过程","stars":4},{"name":"DNA分子的结构与复制","stars":4},{"name":"基因控制蛋白质的合成","stars":5},{"name":"基因、遗传信息及性状的关系","stars":3}]},{"name":"遗传的基本规律","childs":[{"name":"基因的分离定律及其应用","stars":5},{"name":"基因的自由组合定律及其应用","stars":5},{"name":"自由组合定律的变式","stars":3}]},{"name":"伴性遗传和人类遗传病","childs":[{"name":"伴性遗传","stars":5},{"name":"人类遗传病","stars":4}]},{"name":"生物的变异和进化","childs":[{"name":"基因重组和基因突变","stars":5},{"name":"染色体变异","stars":3},{"name":"生物变异在育种上的应用","stars":4},{"name":"现代生物进化理论","stars":5}]},{"name":"人和高等动物的神经调节","childs":[{"name":"反射和人脑的高级功能","stars":4},{"name":"神经冲动的产生与传导","stars":5}]},{"name":"人和高等动物的体液调节","childs":[{"name":"脊椎动物的激素调节","stars":5},{"name":"血糖调节","stars":4},{"name":"水盐平衡调节和体温调节","stars":3}]},{"name":"免疫调节","childs":[{"name":"免疫系统的组成与功能","stars":5},{"name":"免疫系统异常和免疫学应用","stars":3}]},{"name":"植物的激素调节","childs":[{"name":"植物生长素的发现和作用","stars":5},{"name":"其他植物激素及应用","stars":5}]},{"name":"种群和群落","childs":[{"name":"种群的特征与数量变化","stars":5},{"name":"群落的结构与演替","stars":5}]},{"name":"生态系统及生态环境的保护","childs":[{"name":"生态系统的结构","stars":5},{"name":"生态系统的功能","stars":5},{"name":"生态系统的稳定性和生态环境的保护","stars":5}]},{"name":"实验与探究","childs":[{"name":"教材基本实验综合","stars":4},{"name":"实验设计及分析","stars":5}]},{"name":"微生物的利用和生物技术在食品加工中的应用","childs":[{"name":"微生物的利用","stars":3},{"name":"传统发酵技术","stars":3},{"name":"某种微生物数量的测定","stars":3}]},{"name":"酶的应用和生物技术在其他方面的应用","childs":[{"name":"酶的应用","stars":4},{"name":"生物技术在其他方面的应用","stars":3},{"name":"植物组织培养","stars":4}]},{"name":"基因工程","childs":[{"name":"基因工程的原理及技术","stars":5},{"name":"基因工程的应用与发展","stars":4}]},{"name":"细胞工程","childs":[{"name":"植物细胞工程","stars":3},{"name":"动物细胞工程","stars":3}]},{"name":"胚胎工程、生物技术安全性和伦理问题","childs":[{"name":"胚胎工程","stars":5},{"name":"生物技术的安全性和伦理问题","stars":2}]},{"name":"冠词和代词","childs":[{"name":"冠词","stars":3},{"name":"代词","stars":3}]},{"name":"名词和主谓一致","childs":[{"name":"名词","stars":3},{"name":"主谓一致","stars":1}]},{"name":"定语从句和名词性从句","childs":[{"name":"定语从句","stars":3},{"name":"名词性从句","stars":3}]},{"name":"并列连词和状语从句","childs":[{"name":"并列连词","stars":4},{"name":"状语从句","stars":3}]},{"name":"阅读理解","childs":[{"name":"记叙文","stars":5},{"name":"说明文","stars":5},{"name":"议论文","stars":3},{"name":"应用文","stars":2}]},{"name":"完形填空","childs":[{"name":"记叙文","stars":5},{"name":"夹叙夹议文","stars":2},{"name":"说明文/议论文","stars":1}]},{"name":"书面表达","childs":[{"name":"应用文","stars":5},{"name":"议论文","stars":3},{"name":"说明文","stars":3}]},{"name":"古代中国的政治制度","childs":[{"name":"商周时期的政治制度","stars":3},{"name":"秦中央集权制度的形成","stars":3},{"name":"汉到元政治制度的演变","stars":5},{"name":"明清君主专制制度的加强","stars":4}]},{"name":"古代希腊、罗马的政治制度","childs":[{"name":"雅典民主政治","stars":5},{"name":"罗马法","stars":3}]},{"name":"欧美代议制的确立与发展","childs":[{"name":"英国君主立宪制的确立","stars":3},{"name":"美国共和制的确立","stars":3},{"name":"法国共和制、德意志帝国君主立宪制的确立","stars":3}]},{"name":"列强侵略与中国人民的反抗斗争","childs":[{"name":"1840-1900年间列强侵略与中国人民的反抗斗争","stars":4},{"name":"侵华日军的罪行与中国军民的抗日斗争","stars":5}]},{"name":"近代中国的民主革命","childs":[{"name":"太平天国运动","stars":1},{"name":"辛亥革命","stars":4},{"name":"五四运动和中国共产党的成立","stars":3},{"name":"新民主主义革命","stars":5}]},{"name":"从科学社会主义理论到社会主义制度的建立","childs":[{"name":"《共产党宣言》和巴黎公社","stars":2},{"name":"俄国十月革命","stars":2}]},{"name":"现代中国的政治建设与祖国统一","childs":[{"name":"中华人民共和国的成立与民主政治制度的建设","stars":3},{"name":"“文化大革命”及改革开放以来的民主与法制建设","stars":1},{"name":"“一国两制”的理论与实践","stars":2}]},{"name":"现代中国的对外关系","childs":[{"name":"新中国成立初期的重大外交活动与和平共处五项原则","stars":3},{"name":"中国恢复在联合国的合法席位与中美关系正常化和中日邦交正常化","stars":2},{"name":"改革开放以来我国在联合国和地区性国际组织中的重要外交活动","stars":2}]},{"name":"当今世界政治格局的多极化趋势","childs":[{"name":"美苏两极对峙格局的形成","stars":3},{"name":"多极化趋势在曲折中发展","stars":2},{"name":"两极格局的瓦解和多极化趋势的加强","stars":2}]},{"name":"古代中国经济的基本结构与特点","childs":[{"name":"农业的主要耕作方式和土地制度","stars":5},{"name":"手工业的发展","stars":3},{"name":"商业的发展","stars":5},{"name":"资本主义萌芽与“重农抑商”和“海禁”政策","stars":5}]},{"name":"新航路的开辟、殖民扩张与资本主义世界市场的形成和发展","childs":[{"name":"新航路的开辟及荷兰、英国等国的殖民扩张","stars":2},{"name":"工业革命","stars":5}]},{"name":"近代中国经济结构的变动与资本主义的曲折发展","childs":[{"name":"晚清中国经济结构的变化和民族工业的兴起","stars":5},{"name":"民国时期民族工业的曲折发展","stars":3}]},{"name":"中国特色社会主义建设的道路","childs":[{"name":"20世纪50 —70年代探索社会主义建设道路的实践","stars":5},{"name":"党的十一届三中全会关于改革开放的决策及家庭联产承包责任制和国有企业改革","stars":2},{"name":"对外开放格局的初步形成及社会主义市场经济体质的建立","stars":2}]},{"name":"中国近现代社会生活的变迁","childs":[{"name":"物质生活和社会习俗的变化","stars":4},{"name":"交通、通讯工具的进步","stars":1},{"name":"大众传媒的发展","stars":2}]},{"name":"世界资本主义经济政策的调整","childs":[{"name":"1929—1933年资本主义世界经济危机","stars":2},{"name":"罗斯福新政","stars":3},{"name":"第二次世界大战后美国等国资本主义的新变化","stars":3}]},{"name":"苏联的社会主义建设","childs":[{"name":"战时共产主义政策和新经济政策","stars":1},{"name":"“斯大林模式”","stars":3},{"name":"从赫鲁晓夫改革到戈尔巴乔夫改革","stars":1}]},{"name":"当今世界经济的全球化趋势","childs":[{"name":"布雷顿森林体系的建立","stars":1},{"name":"世界经济区域集团化","stars":2},{"name":"世界贸易组织和中国的加入","stars":3}]},{"name":"中国传统文化主流思想的演变","childs":[{"name":"春秋战国时期的百家争鸣","stars":3},{"name":"汉代儒学成为正统思想","stars":2},{"name":"宋明理学","stars":4},{"name":"明清之际的儒学思想","stars":3}]},{"name":"西方人文精神的起源与发展","childs":[{"name":"西方人文精神的起源","stars":1},{"name":"文艺复兴和宗教改革","stars":1},{"name":"启蒙运动","stars":5}]},{"name":"古代中国的科学技术与文学艺术","childs":[{"name":"科技成就","stars":3},{"name":"汉字的起源、演变和书画的发展","stars":2},{"name":"文学成就及京剧等剧种的产生和发展","stars":3}]},{"name":"近代以来世界的科学发展历程","childs":[{"name":"经典力学、相对论和量子论","stars":2},{"name":"进化论","stars":2},{"name":"蒸汽机的发明、电气技术的应用及现代信息技术","stars":3}]},{"name":"近代中国的思想解放潮流","childs":[{"name":"维新思想","stars":5},{"name":"新文化运动","stars":3},{"name":"马克思主义在中国的传播","stars":2}]},{"name":"20世纪以来中国重大思想理论成果","childs":[{"name":"孙中山的三民主义","stars":3},{"name":"毛泽东思想","stars":2},{"name":"邓小平理论和“三个代表”重要思想","stars":1}]},{"name":"现代中国的科技、教育与文学艺术","childs":[{"name":"科技发展的主要成就","stars":1},{"name":"“百花齐放，百家争鸣”方针","stars":1},{"name":"教育事业的发展","stars":2}]},{"name":"19世纪以来的世界文学艺术","childs":[{"name":"文学的主要成就","stars":2},{"name":"美术、音乐及影视艺术","stars":2}]},{"name":"历史上的重大改革","childs":[{"name":"中国历史上的重大改革","stars":3},{"name":"外国历史上的重大改革","stars":2}]},{"name":"近代社会的民主思想与实践","childs":[{"name":"近代欧洲的民主思想及在欧洲的实践","stars":2},{"name":"近代中国的民主思想及在中国的实践","stars":3}]},{"name":"20世纪的战争与和平","childs":[{"name":"20世纪的战争","stars":3},{"name":"20世纪的和平","stars":2}]},{"name":"中外历史人物评说","childs":[{"name":"古代先哲与古今著名政治家","stars":3},{"name":"古今中外的科学家","stars":1}]},{"name":"学科工具","childs":[{"name":"经纬网与地图","stars":1},{"name":"等高线地形图及地形剖面图","stars":4},{"name":"“3S”技术","stars":5}]},{"name":"宇宙中的地球","childs":[{"name":"地球的宇宙环境与圈层结构","stars":3},{"name":"地球运动特征与四季、五带","stars":2},{"name":"时差","stars":3},{"name":"正午太阳高度的变化","stars":2},{"name":"昼夜交替与昼夜长短的变化","stars":3}]},{"name":"地表形态的塑造","childs":[{"name":"三类岩石与地壳物质循环","stars":3},{"name":"内力作用与地貌","stars":4},{"name":"外力作用与地貌","stars":5}]},{"name":"地球上的大气","childs":[{"name":"大气受热过程","stars":3},{"name":"热力环流与风","stars":1},{"name":"全球性大气环流","stars":3},{"name":"锋面与天气","stars":3},{"name":"高、低压系统与天气","stars":2},{"name":"气候类型分布、特征及成因","stars":5}]},{"name":"地球上的水","childs":[{"name":"水循环与陆地水体相互关系","stars":5},{"name":"洋流及其对地理环境的影响","stars":5}]},{"name":"自然地理环境的整体性和差异性","childs":[{"name":"自然地理环境的整体性","stars":3},{"name":"地理环境的地域分异规律","stars":5}]},{"name":"自然环境对人类活动的影响","childs":[{"name":"地表形态与人类活动","stars":2},{"name":"全球气候变化对人类活动的影响","stars":3},{"name":"自然资源对人类的影响","stars":3}]},{"name":"人口的变化","childs":[{"name":"人口数量变化与人口问题","stars":3},{"name":"人口迁移与人口容量","stars":4}]},{"name":"城市与城市化","childs":[{"name":"城市空间结构与城市规划","stars":5},{"name":"城市区位与城市等级体系","stars":2},{"name":"城市化及其影响","stars":3}]},{"name":"农业地域的形成与发展","childs":[{"name":"农业区位因素","stars":5},{"name":"农业地域类型","stars":3}]},{"name":"工业地域的形成与发展","childs":[{"name":"工业区位因素","stars":5},{"name":"工业地域","stars":4}]},{"name":"人类活动的地域联系","childs":[{"name":"地域联系方式与区位","stars":4},{"name":"交通运输的影响","stars":2}]},{"name":"区域地理环境与可持续发展","childs":[{"name":"人地关系与可持续发展","stars":4},{"name":"区域地理环境差异与发展","stars":4},{"name":"区域环境、发展问题与解决措施","stars":5}]},{"name":"区域自然资源综合开发利用","childs":[{"name":"河流流域的综合开发","stars":3},{"name":"区域能源、矿产资源的综合开发利用","stars":3},{"name":"资源的跨区域调配","stars":2}]},{"name":"区域经济发展","childs":[{"name":"区域农业发展","stars":5},{"name":"区域工业化与城市化","stars":3},{"name":"产业转移","stars":5}]},{"name":"世界地理","childs":[{"name":"世界地理概况","stars":5},{"name":"亚洲","stars":3},{"name":"非洲","stars":3},{"name":"美洲","stars":5},{"name":"欧洲","stars":3},{"name":"大洋洲和极地地区","stars":2}]},{"name":"中国地理","childs":[{"name":"中国自然地理概况","stars":5},{"name":"中国人文地理概况","stars":5},{"name":"中国不同尺度的区域","stars":5}]},{"name":"旅游地理","childs":[{"name":"旅游资源的类型、分布与评价","stars":5},{"name":"旅游规划、旅游与区域发展","stars":4}]},{"name":"自然灾害与防治","childs":[{"name":"地质灾害与防治","stars":4},{"name":"气象灾害与其他灾害","stars":5}]},{"name":"环境保护","childs":[{"name":"环境与环境问题","stars":5},{"name":"环境污染与防治、环境管理","stars":3}]},{"name":"生活与消费","childs":[{"name":"货币的本质","stars":3},{"name":"货币的种类与形式","stars":3},{"name":"价格的决定与变动","stars":5},{"name":"价格变动对经济生活的影响","stars":4},{"name":"消费及其类型","stars":4},{"name":"树立正确的消费观","stars":2}]},{"name":"生产、劳动与经营","childs":[{"name":"生产与消费","stars":3},{"name":"我国的基本经济制度","stars":2},{"name":"生产的微观主体——企业","stars":5},{"name":"劳动者","stars":3},{"name":"商业银行","stars":3},{"name":"投资与融资","stars":4}]},{"name":"收入与分配","childs":[{"name":"分配制度","stars":1},{"name":"效率与公平","stars":5},{"name":"国家财政","stars":4},{"name":"征税与纳税","stars":3}]},{"name":"发展社会主义市场经济","childs":[{"name":"市场经济基本原理","stars":5},{"name":"社会主义市场经济","stars":5},{"name":"科学发展观和小康社会的经济建设","stars":5},{"name":"经济全球化","stars":5},{"name":"国际经济竞争与合作","stars":4}]},{"name":"公民的政治生活","childs":[{"name":"我国的国家性质","stars":2},{"name":"我国公民的权利和义务","stars":4},{"name":"我国公民政治参与的途径和方式","stars":5}]},{"name":"为人民服务的政府","childs":[{"name":"我国政府的职能和责任","stars":5},{"name":"政府权利和行使与监督和政府的威信","stars":5}]},{"name":"发展社会主义民主政治","childs":[{"name":"我国的人民代表大会制度","stars":5},{"name":"我国的政党制度","stars":5},{"name":"我国的民主区域自治制度及宗教政策","stars":4}]},{"name":"当代国际社会","childs":[{"name":"国际社会的成员","stars":2},{"name":"处理国际关系的决定性因素","stars":3},{"name":"世界政治经济发展的基本趋势","stars":3},{"name":"我国独立自主和平外交政策","stars":3}]},{"name":"文化与生活","childs":[{"name":"文化与社会","stars":4},{"name":"文化对人的影响","stars":5}]},{"name":"文化传承与创新","childs":[{"name":"文化的多样性与文化传播","stars":5},{"name":"文化的继承与发展","stars":4},{"name":"文化创新","stars":5}]},{"name":"中华文化与民族精神","childs":[{"name":"灿烂的中华文化","stars":4},{"name":"弘扬和培育民族精神","stars":3}]},{"name":"发展中国特色社会主义文化","childs":[{"name":"走进文化生活","stars":3},{"name":"建设社会主义文化强国","stars":5},{"name":"加强社会主义思想道德建设","stars":4}]},{"name":"生活智慧与时代精神","childs":[{"name":"哲学是什么","stars":1},{"name":"哲学基本问题及基本派别","stars":2},{"name":"马克思主义哲学","stars":1}]},{"name":"探索世界与追求真理","childs":[{"name":"物质与运动","stars":2},{"name":"物质和意识的辩证关系","stars":5},{"name":"客观规律与意识的能动作用","stars":5},{"name":"实践与认识","stars":5},{"name":"真理","stars":3},{"name":"认识过程","stars":4}]},{"name":"思想方法与创新意识","childs":[{"name":"唯物辩证法的联系观","stars":5},{"name":"唯物辩证法的发展观","stars":4},{"name":"唯物辩证法的矛盾观","stars":5},{"name":"辩证的否定观与创新意识","stars":4}]},{"name":"认识社会与价值选择","childs":[{"name":"社会存在与社会意识","stars":4},{"name":"人类社会的基本矛盾","stars":2},{"name":"人民群众是历史的创造者","stars":3},{"name":"人生价值","stars":2},{"name":"价值判断与价值选择","stars":2},{"name":"价值的创造与实现","stars":4}]},{"name":"经济学常识","childs":[{"name":"古典经济学巨匠的理论遗产","stars":3},{"name":"马克思主义经济学的伟大贡献","stars":2},{"name":"西方国家现代市场经济的兴起与主要模式","stars":2},{"name":"社会主义经济理论的初期探讨","stars":2},{"name":"中国社会主义市场经济的探索","stars":3}]},{"name":"国家和国际组织常识","childs":[{"name":"各具特色的国家和国际组织","stars":2},{"name":"君主立宪制和民主共和制","stars":2},{"name":"联邦制、两党制、三权分立","stars":3},{"name":"民主集中制","stars":2},{"name":"日益重要的国际组织","stars":3}]}]